bemi/__init__.py
bemi/managers.py
bemi/middleware.py
bemi/mixins.py
bemi/models.py
bemi/querysets.py
bemi/routers.py
bemi/migrations/0001_initial.py
bemi/migrations/0002_bemichange.py
bemi/migrations/__init__.py
bemi_django-0.1.3.dist-info/LICENCE
bemi_django-0.1.3.dist-info/METADATA
bemi_django-0.1.3.dist-info/WHEEL
bemi_django-0.1.3.dist-info/top_level.txt
bemi_django-0.1.3.dist-info/RECORD
