Metadata-Version: 2.1
Name: bemi-django
Version: 0.1.3
Summary: Automatic data change tracking for Django
Author-email: Arjun Lall <arjun@bemi.io>
Project-URL: Homepage, https://github.com/BemiHQ/bemi-django
Project-URL: Issues, https://github.com/BemiHQ/bemi-django/issues
Project-URL: Documentation, https://docs.bemi.io/orms/django
Classifier: Intended Audience :: Information Technology
Classifier: Intended Audience :: System Administrators
Classifier: Intended Audience :: Developers
Classifier: Operating System :: OS Independent
Classifier: Topic :: Software Development :: Libraries :: Application Frameworks
Classifier: Topic :: Software Development :: Libraries :: Python Modules
Classifier: Topic :: Software Development :: Libraries
Classifier: Topic :: Software Development
Classifier: Topic :: Database
Classifier: Programming Language :: Python
Classifier: Programming Language :: Python :: 3
Classifier: Programming Language :: Python :: 3 :: Only
Classifier: Programming Language :: Python :: 3.8
Classifier: Programming Language :: Python :: 3.9
Classifier: Programming Language :: Python :: 3.10
Classifier: Programming Language :: Python :: 3.11
Classifier: Programming Language :: Python :: 3.12
Classifier: License :: OSI Approved :: GNU Lesser General Public License v3 (LGPLv3)
Requires-Python: >=3.8
License-File: LICENCE
Requires-Dist: Django>=3.2
